codepic/__init__.py
codepic/cli.py
codepic/render.py
codepic-0.2.0.dist-info/LICENSE
codepic-0.2.0.dist-info/METADATA
codepic-0.2.0.dist-info/WHEEL
codepic-0.2.0.dist-info/entry_points.txt
codepic-0.2.0.dist-info/RECORD
