Metadata-Version: 2.1
Name: codepic
Version: 0.2.0
Summary: Capture code in a picture
Home-page: https://github.com/automas-dev/codepic
License: MIT
Author: Thomas Harrison
Author-email: theharrisoncrafter@gmail.com
Requires-Python: >=3.10,<4.0
Classifier: License :: OSI Approved :: MIT License
Classifier: Operating System :: POSIX :: Linux
Classifier: Programming Language :: Python :: 3
Classifier: Programming Language :: Python :: 3.10
Classifier: Programming Language :: Python :: 3.11
Classifier: Programming Language :: Python :: 3.12
Classifier: Programming Language :: Python :: 3.13
Requires-Dist: click (>=8.1.8,<9.0.0)
Requires-Dist: pillow (>=11.1.0,<12.0.0)
Requires-Dist: pygments (>=2.19.1,<3.0.0)
Project-URL: Repository, https://github.com/automas-dev/codepic
